README-public-pypi.md
cisco_radkit_service-1.9.0.dist-info/METADATA
cisco_radkit_service-1.9.0.dist-info/WHEEL
cisco_radkit_service-1.9.0.dist-info/entry_points.txt
cisco_radkit_service-1.9.0.dist-info/licenses/LICENSE.md
radkit_service/LICENSE.html
radkit_service/LICENSE.md
radkit_service/__init__.py
radkit_service/__main__.py
radkit_service/access_token_responder.py
radkit_service/actions/__init__.py
radkit_service/actions/enroll.py
radkit_service/actions/reset.py
radkit_service/anonymization/__init__.py
radkit_service/anonymization/base.py
radkit_service/anonymization/cryptopan.py
radkit_service/anonymization/default.py
radkit_service/anonymization/synchronizer.py
radkit_service/anonymization/text_anonymizer.py
radkit_service/backends/__init__.py
radkit_service/backends/devices_backend/__init__.py
radkit_service/backends/devices_backend/base.py
radkit_service/backends/devices_backend/combined.py
radkit_service/backends/devices_backend/database.py
radkit_service/backends/devices_backend/dummy.py
radkit_service/backends/devices_backend/model_conversion.py
radkit_service/capabilities_responder.py
radkit_service/certificate_service.py
radkit_service/cli/__init__.py
radkit_service/cli/control/__init__.py
radkit_service/cli/control/commands/__init__.py
radkit_service/cli/control/commands/_lib.py
radkit_service/cli/control/commands/_types.py
radkit_service/cli/control/commands/admins.py
radkit_service/cli/control/commands/devices.py
radkit_service/cli/control/commands/labels.py
radkit_service/cli/control/commands/remote_users.py
radkit_service/cli/control/commands/roles.py
radkit_service/cli/control/commands/system.py
radkit_service/cli/control/helpers.py
radkit_service/cli/control/main.py
radkit_service/cli/gui/__init__.py
radkit_service/cli/gui/main.py
radkit_service/cli/medic/__init__.py
radkit_service/cli/medic/main.py
radkit_service/cli/radkit_command.py
radkit_service/cli/script_exceptions.py
radkit_service/cli/service/__init__.py
radkit_service/cli/service/commands/__init__.py
radkit_service/cli/service/commands/_helpers.py
radkit_service/cli/service/commands/commands.py
radkit_service/cli/service/commands/open.py
cisco_radkit_service-1.9.0.dist-info/RECORD
