Metadata-Version: 2.1
Name: cisco_radkit_service
Version: 1.9.0
Summary: Cisco RADKit Service
Keywords: cisco,remote,automation
Author-Email: "Cisco Systems Inc." <radkit@cisco.com>
License: Cisco Remote Automation Development Kit (RADKit) -- Copyright (c) 2018-2025 by Cisco Systems, Inc.
Classifier: Development Status :: 5 - Production/Stable
Classifier: Development Status :: 6 - Mature
Classifier: Intended Audience :: Developers
Classifier: Intended Audience :: Information Technology
Classifier: Intended Audience :: System Administrators
Classifier: Intended Audience :: Telecommunications Industry
Classifier: License :: Other/Proprietary License
Classifier: Operating System :: MacOS
Classifier: Operating System :: Microsoft :: Windows
Classifier: Operating System :: POSIX :: Linux
Classifier: Programming Language :: Python :: 3 :: Only
Classifier: Programming Language :: Python :: 3.10
Classifier: Programming Language :: Python :: 3.11
Classifier: Programming Language :: Python :: 3.12
Classifier: Programming Language :: Python :: 3.13
Classifier: Programming Language :: Python :: Implementation :: CPython
Classifier: Topic :: System :: Systems Administration
Project-URL: HomePage, https://radkit.cisco.com
Project-URL: Documentation, https://radkit.cisco.com/docs/index.html
Requires-Python: <3.14,>=3.10
Requires-Dist: cisco_radkit_common==1.9.0
Requires-Dist: prompt-toolkit<4.0,>=3.0.50
Requires-Dist: ptpython<4.0,>=3.0.22
Requires-Dist: pydantic==2.11.7
Requires-Dist: email-validator>=2.0.0
Requires-Dist: pydantic-settings~=2.7.1
Requires-Dist: fastapi>=0.100.0
Requires-Dist: hypercorn<0.17.0,>=0.14.4
Requires-Dist: lxml<7.0,>=6.0.0
Requires-Dist: pyang!=2.6.0,<3.0,>=2.0
Requires-Dist: ncclient<0.6.16,>=0.6.12
Requires-Dist: asyncssh[pyOpenSSL]<3.0,>=2.14.2
Requires-Dist: xmltodict<1.0,>=0.14.0
Requires-Dist: regex>=2024.5.10
Requires-Dist: psutil<8.0,>=5.9.0
Requires-Dist: PyYAML<7.0,>=6.0
Requires-Dist: httpx>=0.26.0
Requires-Dist: httpcore>=1.0.4
Requires-Dist: python-multipart!=0.0.17,<0.1.0,>=0.0.15
Requires-Dist: telnetlib3<3.0,>=2.0.0
Requires-Dist: aiohttp<4.0,>=3.9
Requires-Dist: multidict<7.0,>=4.5
Requires-Dist: click!=8.1.0,!=8.1.4,!=8.1.5,<8.2.0,>=8.0.1
Requires-Dist: asyncinotify<5.0,>=4.0; sys_platform == "linux"
Requires-Dist: pywin32>=304; sys_platform == "win32"
Requires-Dist: tacacs_plus==2.6
Requires-Dist: pyzipper<0.4,>=0.3.6
